pdf_password_remover/__init__.py
pdf_password_remover/main.py
pdf_password_remover/utils/__init__.py
pdf_password_remover/utils/pdf_utils.py
pdf_password_remover-0.3.0.dist-info/LICENSE
pdf_password_remover-0.3.0.dist-info/METADATA
pdf_password_remover-0.3.0.dist-info/WHEEL
pdf_password_remover-0.3.0.dist-info/entry_points.txt
pdf_password_remover-0.3.0.dist-info/RECORD
