Metadata-Version: 2.3
Name: pdf-password-remover
Version: 0.3.0
Summary: A Python based CLI tool to remove passwords from PDF files.
Author: Ronald Erosa
Author-email: thecasualdev@gmail.com
Requires-Python: >=3.9
Classifier: Programming Language :: Python :: 3
Classifier: Programming Language :: Python :: 3.9
Classifier: Programming Language :: Python :: 3.10
Classifier: Programming Language :: Python :: 3.11
Classifier: Programming Language :: Python :: 3.12
Classifier: Programming Language :: Python :: 3.13
Requires-Dist: pycryptodome (>=3.23.0,<4.0.0)
Requires-Dist: pypdf2 (>=3.0.1,<4.0.0)
Requires-Dist: pytest (>=8.3.5,<9.0.0)
Requires-Dist: tk
Requires-Dist: tkinterdnd2 (>=0.3.0,<0.4.0)
Requires-Dist: typer (>=0.16.0,<0.17.0)
